README.rst
requirements.txt
setup.py
gapi/__init__.py
gapi/adwords.py
gapi/analytics.py
gapi/core.py
gapi/exceptions.py
gapi/test_utils.py
gapi/utils.py
gapi/facade/__init__.py
gapi/facade/calls.py
gapi/facade/calls_criterions.py
gapi/facade/calls_extensions.py
gapi/facade/calls_optimization.py
gapi/facade/calls_stats.py
gapi/facade/core.py
gapi/facade/mutate.py
gapi/facade/param_fields.py
gapi/facade/result_fields.py
gapi/facade/utils.py
gapi_wrapper.egg-info/PKG-INFO
gapi_wrapper.egg-info/SOURCES.txt
gapi_wrapper.egg-info/dependency_links.txt
gapi_wrapper.egg-info/requires.txt
gapi_wrapper.egg-info/top_level.txt