Metadata-Version: 1.1
Name: gapi-wrapper
Version: 0.3.8
Summary: Wrapper to Google API
Home-page: https://bitbucket.org/suguby/gapi-wrapper
Author: Suguby
Author-email: suguby@gmail.com
License: MIT
Keywords: google api adwords analytics
Platform: UNKNOWN
Classifier: Development Status :: 3 - Alpha
Classifier: Intended Audience :: Developers
Classifier: License :: OSI Approved :: MIT License
Classifier: Natural Language :: English
Classifier: Natural Language :: Russian
Classifier: Programming Language :: Python :: 2.7
Classifier: Programming Language :: Python :: 3.5
